fabricatio_actions/__init__.py
fabricatio_actions/py.typed
fabricatio_actions/actions/__init__.py
fabricatio_actions/actions/fs.py
fabricatio_actions/actions/output.py
fabricatio_actions/models/__init__.py
fabricatio_actions/models/generic.py
tests/test_actions.py
fabricatio_actions-0.1.12.dist-info/METADATA
fabricatio_actions-0.1.12.dist-info/WHEEL
fabricatio_actions-0.1.12.dist-info/licenses/LICENSE
fabricatio_actions-0.1.12.dist-info/RECORD
